LICENSE
README.rst
setup.py
bbmix/__init__.py
bbmix/version.py
bbmix.egg-info/PKG-INFO
bbmix.egg-info/SOURCES.txt
bbmix.egg-info/dependency_links.txt
bbmix.egg-info/requires.txt
bbmix.egg-info/top_level.txt
bbmix/models/__init__.py
bbmix/models/betabin_mix.py
bbmix/models/betabin_mix_vb.py
bbmix/models/binomial_mix.py
bbmix/models/binomial_mix_sparse.py
bbmix/models/binomial_mix_vb.py
bbmix/models/hypothesis_test.py
bbmix/models/model_base.py
bbmix/models/statistics.py