Metadata-Version: 2.1
Name: bbmix
Version: 0.2.2
Summary: BBMix: inference of beta-binomial mixture model
Home-page: https://github.com/statbiomed/betabinmix
Author: ['Chen Qiao', 'Yuanhua Huang']
Author-email: example@hku.hk
License: Apache-2.0
Keywords: beta binomial distribution,mixture model,EM algorithm
Provides-Extra: docs
License-File: LICENSE
